[
    {
        "full_name": "quan nguyen",
        "email": "1",
        "password": "1"
    },
    {
        "full_name": "quan ngu",
        "email": "quan",
        "password": "c4ca4238a0b923820dcc509a6f75849b"
    },
    {
        "full_name": "2",
        "username": "2",
        "password": "c81e728d9d4c2f636f067f89cc14862c"
    },
    {
        "full_name": "6",
        "username": "6",
        "password": "1679091c5a880faf6fb5e6087eb1b2dc"
    },
    {
        "full_name": "a",
        "username": "a",
        "password": "0cc175b9c0f1b6a831c399e269772661"
    }
]